odoo/addons/project_sale_link/README.rst
odoo/addons/project_sale_link/__init__.py
odoo/addons/project_sale_link/__manifest__.py
odoo/addons/project_sale_link/i18n/it.po
odoo/addons/project_sale_link/i18n/project_sale_link.pot
odoo/addons/project_sale_link/models/__init__.py
odoo/addons/project_sale_link/models/project_project.py
odoo/addons/project_sale_link/readme/CONTRIBUTORS.rst
odoo/addons/project_sale_link/readme/DESCRIPTION.rst
odoo/addons/project_sale_link/readme/USAGE.rst
odoo/addons/project_sale_link/static/description/icon.png
odoo/addons/project_sale_link/static/description/index.html
odoo/addons/project_sale_link/tests/__init__.py
odoo/addons/project_sale_link/tests/test_project_sale_link.py
odoo/addons/project_sale_link/views/project_project.xml
odoo13_addon_project_sale_link-13.0.1.0.1.dev5.dist-info/METADATA
odoo13_addon_project_sale_link-13.0.1.0.1.dev5.dist-info/WHEEL
odoo13_addon_project_sale_link-13.0.1.0.1.dev5.dist-info/top_level.txt
odoo13_addon_project_sale_link-13.0.1.0.1.dev5.dist-info/RECORD
